CHANGES.txt
CREDITS.txt
README.txt
TODO.txt
bootstrap.py
buildout.cfg
setup.py
test-plone-2.5.cfg
test-plone-3.3.x.cfg
test-plone-4.0.x.cfg
Products/__init__.py
Products.PressRoom.egg-info/PKG-INFO
Products.PressRoom.egg-info/SOURCES.txt
Products.PressRoom.egg-info/dependency_links.txt
Products.PressRoom.egg-info/namespace_packages.txt
Products.PressRoom.egg-info/not-zip-safe
Products.PressRoom.egg-info/requires.txt
Products.PressRoom.egg-info/top_level.txt
Products/PressRoom/__init__.py
Products/PressRoom/config.py
Products/PressRoom/configure.zcml
Products/PressRoom/messagefactory_.py
Products/PressRoom/refresh.txt
Products/PressRoom/setuphandlers.py
Products/PressRoom/version.txt
Products/PressRoom/Extensions/Install.py
Products/PressRoom/Extensions/__init__.py
Products/PressRoom/Extensions/utils.py
Products/PressRoom/browser/__init__.py
Products/PressRoom/browser/configure.zcml
Products/PressRoom/browser/pressroom.py
Products/PressRoom/browser/upgrade_folders.py
Products/PressRoom/content/PressClip.py
Products/PressRoom/content/PressContact.py
Products/PressRoom/content/PressRelease.py
Products/PressRoom/content/PressRoom.py
Products/PressRoom/content/__init__.py
Products/PressRoom/i18n/manual.pot
Products/PressRoom/i18n/pressroom-cs.po
Products/PressRoom/i18n/pressroom-de.po
Products/PressRoom/i18n/pressroom-es.po
Products/PressRoom/i18n/pressroom-eu.po
Products/PressRoom/i18n/pressroom-it.po
Products/PressRoom/i18n/pressroom-plone-cs.po
Products/PressRoom/i18n/pressroom-plone-de.po
Products/PressRoom/i18n/pressroom-plone-es.po
Products/PressRoom/i18n/pressroom-plone-eu.po
Products/PressRoom/i18n/pressroom-plone-it.po
Products/PressRoom/i18n/pressroom-plone.pot
Products/PressRoom/i18n/pressroom.pot
Products/PressRoom/i18n/usei18ndude.sh
Products/PressRoom/interfaces/__init__.py
Products/PressRoom/interfaces/browserviews.py
Products/PressRoom/interfaces/content.py
Products/PressRoom/profiles/default/catalog.xml
Products/PressRoom/profiles/default/cssregistry.xml
Products/PressRoom/profiles/default/factorytool.xml
Products/PressRoom/profiles/default/import_steps.xml
Products/PressRoom/profiles/default/is_pressroom.txt
Products/PressRoom/profiles/default/propertiestool.xml
Products/PressRoom/profiles/default/skins.xml
