Metadata-Version: 1.0
Name: Products.PressRoom
Version: 3.18
Summary: Allows users to instantly create a polished, professional press room, featuring press releases, press clips and press contacts.  Manage an online Press Room within your Plone site.
Home-page: http://plone.org/products/pressroom
Author: Groundwire
Author-email: info@groundwire.org
License: GPL
Keywords: plone press media news release
Platform: UNKNOWN
Classifier: Framework :: Plone
Classifier: Development Status :: 6 - Mature
